mdo_outlier_detector/__init__.py
mdo_outlier_detector/detector.py
mdo_outlier_detector-0.2.2.dist-info/LICENSE
mdo_outlier_detector-0.2.2.dist-info/METADATA
mdo_outlier_detector-0.2.2.dist-info/WHEEL
mdo_outlier_detector-0.2.2.dist-info/top_level.txt
mdo_outlier_detector-0.2.2.dist-info/RECORD
